mycalc/calculator.py
calcy300-0.0.1.dist-info/METADATA
calcy300-0.0.1.dist-info/WHEEL
calcy300-0.0.1.dist-info/top_level.txt
calcy300-0.0.1.dist-info/RECORD
