Metadata-Version: 2.1
Name: calcy300
Version: 0.0.1
Summary: nice calculator
Home-page: https://github.com/Bigowl46/assignment
Download-URL: https://github.com/Bigowl46/assignment/
Author: jaewook
Classifier: Programming Language :: Python :: 3.10
